Metadata-Version: 1.1
Name: proxy-pool
Version: 0.0.2
Summary: A proxy pool which you can get an avaiable proxy http server.
Home-page: https://github.com/wueason/proxy_pool
Author: wueason
Author-email: eason991@gmail.com
License: MIT
Keywords: proxy crawl proxy_pool
Platform: UNKNOWN
Classifier: Development Status :: 4 - Beta
Classifier: Intended Audience :: Developers
Classifier: Topic :: Software Development :: Libraries :: Python Modules
Classifier: Operating System :: OS Independent
Classifier: License :: OSI Approved :: MIT License
Classifier: Programming Language :: Python :: 2.7
